[
    {
        "id":"1",
        "title":"Vacation Planner",
        "description":"Group Project 03",
        "screenshot":"landingpagescreenshot.png",
        "github":"https://github.com/whitspa/dreamvacation",
        "live":"https://safe-inlet-96324.herokuapp.com/"
    },
    
    {
        "id":"2",
        "title":"Employee Tracker",
        "description":"This Content Management System (CMS) utilizes Node.js, Inquirer, and MySQLto manage a company's employee database.",
        "screenshot":"employeetrackerscreenshot.png",
        "github":"https://github.com/whitspa/employeetracker.git",
        "live":"https://drive.google.com/file/d/1yv_eKQaRSSX0LX87qxeb6i4vWA8ETJmc/view "
    },

    {
        "id":"3",
        "title":"Note Taker",
        "description":"This Note Taker app can be used to write and save notes. It uses an Express.js back end and saves and retrieves note data to a JSON file.",
        "screenshot":"notetakerscreenshot.png",
        "github":"https://github.com/whitspa/notetaker.git",
        "live":"https://hidden-thicket-42324.herokuapp.com/"
    },

    {
        "id":"4",
        "title":"Readme Generator",
        "description":"Application which creates professional README based on user input",
        "screenshot":"readmegeneratorscreenshot.png",
        "github":"https://github.com/whitspa/readmegenerator.git",
        "live":"https://drive.google.com/file/d/16X8Al0b0zkeaJCYkXvwaJvMxpJ9x4rzj/view "
    },

    {
        "id":"5",
        "title":"Social Network API",
        "description":"Social network web app where users can share their thoughts, react to friends’ thoughts, and create a friend list.",
        "screenshot":"getallusersscreenshot.png",
        "github":"https://github.com/whitspa/socialnetworkapi.git",
        "live":"https://drive.google.com/file/d/113WjFXDYsxbMCP15zEpLe0ZWGWsbYb0i/view"
    },

    {
        "id":"6",
        "title":"Weather Dashboard",
        "description":"This App utilizes the openweather API to allow the user to see the weather outlook for multiple cities.",
        "screenshot":"weatherdashboardscreenshot.png",
        "github":"https://github.com/whitspa/Weather-Dashboard",
        "live":"https://whitspa.github.io/Weather-Dashboard/"
    },

    {
        "id":"7",
        "title":"Ecommerce Back End",
        "description":"Back end solution for an E Commerce site utilizing sequelize and RESTful API.",
        "screenshot":"ecommerce-backend-w-route-testing.png",
        "github":"https://github.com/whitspa/ecommerce-backend.git",
        "live":"https://drive.google.com/file/d/1HJWA0CPuimX5YkDmwSOd1gUO8atoXjPI/view"
    }

]